{
  "across": {
    "1A": "This is the clue 1A",
    "7A": "This is the clue 7A",
    "10A": "This is the clue 10A",
    "11A": "This is the clue 11A",
    "12A": "This is the clue 12A",
    "13A": "This is the clue 13A",
    "14A": "This is the clue 14A",
    "15A": "This is the clue 15A",
    "17A": "This is the clue 17A",
    "18A": "This is the clue 18A",
    "19A": "This is the clue 19A",
    "21A": "This is the clue 21A",
    "25A": "This is the clue 25A",
    "27A": "This is the clue 27A",
    "28A": "This is the clue 31A",
    "31A": "This is the clue 32A",
    "32A": "This is the clue 32A",
    "33A": "This is the clue 33A",
    "36A": "This is the clue 36A",
    "37A": "This is the clue 37A",
    "38A": "This is the clue 10A",
    "39A": "This is the clue 10A"
  },
  "down": {
    "1D": "This is the clue 1D",
    "2D": "This is the clue 2D",
    "3D": "This is the clue 3D",
    "4D": "This is the clue 4D",
    "5D": "This is the clue 5D",
    "6D": "This is the clue 6D",
    "7D": "This is the clue 7D",
    "8D": "This is the clue 8D",
    "9D": "This is the clue 9D",
    "11D": "This is the clue 11D",
    "16D": "This is the clue 16D",
    "18D": "This is the clue 18D",
    "20D": "This is the clue 20D",
    "22D": "This is the clue 22D",
    "23D": "This is the clue 23D",
    "24D": "This is the clue 24D",
    "26D": "This is the clue 26D",
    "28D": "This is the clue 28D",
    "29D": "This is the clue 29D",
    "30D": "This is the clue 30D",
    "34D": "This is the clue 34D",
    "35D": "This is the clue 35D"
  }
}
